geli_python_common/__init__.py
geli_python_common/amqp/__init__.py
geli_python_common/amqp/amqp.py
geli_python_common/amqp/message_bus_connector.py
geli_python_common/amqp/subscriptions.py
geli_python_common/config/__init__.py
geli_python_common/config/upload_app_config.py
geli_python_common/database/__init__.py
geli_python_common/database/dbhelper.py
geli_python_common/dto/__init__.py
geli_python_common/dto/constants.py
geli_python_common/dto/dto.py
geli_python_common/health/__init__.py
geli_python_common/health/health_checks.py
geli_python_common/http/__init__.py
geli_python_common/http/geni_api.py
geli_python_common/mqtt/__init__.py
geli_python_common/mqtt/mqtt.py
geli_python_common/util/__init__.py
geli_python_common/util/constants.py
geli_python_common/util/metrics.py
geli_python_common/util/objective_schema.py
geli_python_common/util/time.py
geli_python_common/util/ts_utils.py
geli_python_common/util/utils.py
geli_python_common-2.0.0.dist-info/METADATA
geli_python_common-2.0.0.dist-info/WHEEL
geli_python_common-2.0.0.dist-info/top_level.txt
geli_python_common-2.0.0.dist-info/RECORD
