Metadata-Version: 2.1
Name: geli-python-common
Version: 2.0.0
Summary: Python common libraries package
Home-page: UNKNOWN
Author: Insung
Author-email: insung.seok@qcells.com
License: UNKNOWN
Platform: UNKNOWN
Requires-Dist: aenum (==2.1.2)
Requires-Dist: alembic (==1.6.0)
Requires-Dist: amqp (==2.4.0)
Requires-Dist: APScheduler (==3.5.3)
Requires-Dist: arrow (==0.17.0)
Requires-Dist: attrs (==18.2.0)
Requires-Dist: billiard (==3.5.0.5)
Requires-Dist: bleach (==3.1.0)
Requires-Dist: certifi (==2018.11.29)
Requires-Dist: chardet (==3.0.4)
Requires-Dist: Click (==7.0)
Requires-Dist: coverage (==4.5.2)
Requires-Dist: docutils (==0.14)
Requires-Dist: idna (==2.8)
Requires-Dist: itsdangerous (==1.1.0)
Requires-Dist: Jinja2 (==2.10)
Requires-Dist: kombu (==4.2.1)
Requires-Dist: Logbook (==1.4.1)
Requires-Dist: Mako (==1.0.7)
Requires-Dist: MarkupSafe (==1.1.1)
Requires-Dist: nose2 (==0.8.0)
Requires-Dist: numpy (==1.19.0)
Requires-Dist: pandas (==1.0.5)
Requires-Dist: pika (==1.0.1)
Requires-Dist: pkginfo (==1.5.0.1)
Requires-Dist: psycopg2 (==2.7.6.1)
Requires-Dist: Pygments (==2.3.1)
Requires-Dist: python-dateutil (==2.8.1)
Requires-Dist: python-dotenv (==0.10.1)
Requires-Dist: python-editor (==1.0.3)
Requires-Dist: pytz (==2020.1)
Requires-Dist: readme-renderer (==24.0)
Requires-Dist: requests (==2.21.0)
Requires-Dist: requests-toolbelt (==0.9.1)
Requires-Dist: responses (==0.10.15)
Requires-Dist: six (==1.15.0)
Requires-Dist: SQLAlchemy (==1.3.0)
Requires-Dist: SQLAlchemy-Utils (==0.34.2)
Requires-Dist: tqdm (==4.31.1)
Requires-Dist: twine (==1.13.0)
Requires-Dist: tzlocal (==1.5.1)
Requires-Dist: urllib3 (==1.24.1)
Requires-Dist: vine (==1.2.0)
Requires-Dist: webencodings (==0.5.1)
Requires-Dist: Werkzeug (==0.14.1)
Requires-Dist: paho-mqtt (==1.3.1)
